{
  "id": 12,
  "title": "Thursday Boot Co. Captain Chelsea Boot",
  "price": 199.99,
  "description": "The Captain Chelsea Boot from Thursday Boot Co. is handcrafted from full-grain leather with a sleek, minimalist silhouette. Featuring a rubber outsole for all-day wear, elastic side panels for easy on-and-off, and genuine leather lining that molds to your foot over time. Business or weekend — this boot does both.",
  "category": "boots",
  "image": "https://placehold.co/400x400/78350f/ffffff?text=Thursday+Chelsea+Boot",
  "rating": {
    "rate": 4.7,
    "count": 389
  },
  "brand": "Thursday Boot Co.",
  "mpn": "THURSD-0012",
  "gtin": "2000012070006",
  "condition": "new",
  "color": "Brown",
  "material": "Full-grain Leather",
  "availability": "in_stock",
  "inventory_quantity": 173,
  "google_product_category": "187",
  "item_group_id": "GRP-12",
  "sizes": [
    "US 7",
    "US 8",
    "US 9",
    "US 10",
    "US 11",
    "US 12"
  ],
  "variants": [
    {
      "size": "US 7",
      "color": "Brown",
      "sku": "SKU-12-7",
      "gtin": "2000012070006",
      "availability": "in_stock",
      "inventory_quantity": 28
    },
    {
      "size": "US 8",
      "color": "Brown",
      "sku": "SKU-12-8",
      "gtin": "2000012080005",
      "availability": "in_stock",
      "inventory_quantity": 31
    },
    {
      "size": "US 9",
      "color": "Brown",
      "sku": "SKU-12-9",
      "gtin": "2000012090004",
      "availability": "in_stock",
      "inventory_quantity": 34
    },
    {
      "size": "US 10",
      "color": "Brown",
      "sku": "SKU-12-10",
      "gtin": "2000012100000",
      "availability": "in_stock",
      "inventory_quantity": 37
    },
    {
      "size": "US 11",
      "color": "Brown",
      "sku": "SKU-12-11",
      "gtin": "2000012110009",
      "availability": "in_stock",
      "inventory_quantity": 40
    },
    {
      "size": "US 12",
      "color": "Brown",
      "sku": "SKU-12-12",
      "gtin": "2000012120008",
      "availability": "in_stock",
      "inventory_quantity": 3
    }
  ],
  "images": [
    "https://placehold.co/400x400/78350f/ffffff?text=Thursday+Chelsea+Boot"
  ]
}
